agency/__init__.py
agency/agent.py
agency/logger.py
agency/processor.py
agency/queue.py
agency/resources.py
agency/schema.py
agency/space.py
agency/spaces/__init__.py
agency/spaces/amqp_space.py
agency/spaces/local_space.py
agency-1.6.3.dist-info/LICENSE
agency-1.6.3.dist-info/METADATA
agency-1.6.3.dist-info/WHEEL
agency-1.6.3.dist-info/RECORD
