Metadata-Version: 2.1
Name: agency
Version: 1.6.3
Summary: A fast and minimal framework for building agent-integrated systems
License: GPL-3.0
Author: Daniel Rodriguez
Requires-Python: >=3.9,<4.0
Classifier: License :: OSI Approved :: GNU General Public License v3 (GPLv3)
Classifier: Programming Language :: Python :: 3
Classifier: Programming Language :: Python :: 3.9
Classifier: Programming Language :: Python :: 3.10
Classifier: Programming Language :: Python :: 3.11
Requires-Dist: colorlog (>=6.7.0,<7.0.0)
Requires-Dist: docstring-parser (>=0.15,<0.16)
Requires-Dist: kombu (>=5.3.1,<6.0.0)
Requires-Dist: pydantic (>=1.8)
Requires-Dist: pygments (>=2.16.1,<3.0.0)
